{
  "pointList": [
    {
      "origin": "walk",
      "ID": 0,
      "position": {
        "x": 207.0,
        "y": 114.0
      },
      "radius": 6.0
    },
    {
      "origin": "squashMe",
      "ID": 1,
      "position": {
        "x": 319.0,
        "y": 108.0
      },
      "radius": 6.0
    }
  ],
  "animationBoxList": [
    {
      "ID": 0,
      "trigger": "walk",
      "x": 122.0,
      "y": 124.0,
      "width": 166.0,
      "frameList": [
        {
          "sprite": {
            "width": 16,
            "height": 24,
            "texture": {
              "filePath": "assets/images/spritesheets/turtle.png"
            },
            "textureCoordinates": [
              {
                "x": 0.25,
                "y": 1.0
              },
              {
                "x": 0.25,
                "y": 0.0
              },
              {
                "x": 0.0,
                "y": 0.0
              },
              {
                "x": 0.0,
                "y": 1.0
              }
            ]
          },
          "frameTime": 0.25
        },
        {
          "sprite": {
            "width": 16,
            "height": 24,
            "texture": {
              "filePath": "assets/images/spritesheets/turtle.png"
            },
            "textureCoordinates": [
              {
                "x": 0.5,
                "y": 1.0
              },
              {
                "x": 0.5,
                "y": 0.0
              },
              {
                "x": 0.25,
                "y": 0.0
              },
              {
                "x": 0.25,
                "y": 1.0
              }
            ]
          },
          "frameTime": 0.25
        }
      ],
      "doesLoop": true,
      "pointFields": [
        {
          "name": "up",
          "position": {
            "x": 122.0,
            "y": 60.0
          },
          "size": {
            "x": 126.0,
            "y": 10.0
          },
          "pointList": []
        },
        {
          "name": "right",
          "position": {
            "x": 205.0,
            "y": 124.0
          },
          "size": {
            "x": 10.0,
            "y": 88.0
          },
          "pointList": [
            {
              "origin": "walk",
              "ID": 0,
              "position": {
                "x": 207.0,
                "y": 114.0
              },
              "radius": 6.0
            }
          ]
        },
        {
          "name": "down",
          "position": {
            "x": 122.0,
            "y": 188.0
          },
          "size": {
            "x": 126.0,
            "y": 10.0
          },
          "pointList": []
        },
        {
          "name": "left",
          "position": {
            "x": 39.0,
            "y": 124.0
          },
          "size": {
            "x": 10.0,
            "y": 88.0
          },
          "pointList": []
        }
      ]
    },
    {
      "ID": 2,
      "trigger": "squashMe",
      "x": 405.0,
      "y": 108.0,
      "width": 166.0,
      "frameList": [
        {
          "sprite": {
            "width": 16,
            "height": 24,
            "texture": {
              "filePath": "assets/images/spritesheets/turtle.png"
            },
            "textureCoordinates": [
              {
                "x": 0.75,
                "y": 1.0
              },
              {
                "x": 0.75,
                "y": 0.0
              },
              {
                "x": 0.5,
                "y": 0.0
              },
              {
                "x": 0.5,
                "y": 1.0
              }
            ]
          },
          "frameTime": 0.25
        }
      ],
      "doesLoop": false,
      "pointFields": [
        {
          "name": "up",
          "position": {
            "x": 405.0,
            "y": 44.0
          },
          "size": {
            "x": 126.0,
            "y": 10.0
          },
          "pointList": []
        },
        {
          "name": "right",
          "position": {
            "x": 488.0,
            "y": 108.0
          },
          "size": {
            "x": 10.0,
            "y": 88.0
          },
          "pointList": []
        },
        {
          "name": "down",
          "position": {
            "x": 405.0,
            "y": 172.0
          },
          "size": {
            "x": 126.0,
            "y": 10.0
          },
          "pointList": []
        },
        {
          "name": "left",
          "position": {
            "x": 322.0,
            "y": 108.0
          },
          "size": {
            "x": 10.0,
            "y": 88.0
          },
          "pointList": [
            {
              "origin": "squashMe",
              "ID": 1,
              "position": {
                "x": 319.0,
                "y": 108.0
              },
              "radius": 6.0
            }
          ]
        }
      ]
    }
  ]
}